schwab_client-2.0.2.dist-info/licenses/LICENSE
schwabpy/__init__.py
schwabpy/accounts.py
schwabpy/auth.py
schwabpy/client.py
schwabpy/exceptions.py
schwabpy/market_data.py
schwabpy/models.py
schwabpy/orders.py
schwabpy/utils.py
schwab_client-2.0.2.dist-info/METADATA
schwab_client-2.0.2.dist-info/WHEEL
schwab_client-2.0.2.dist-info/top_level.txt
schwab_client-2.0.2.dist-info/RECORD
