Metadata-Version: 2.4
Name: schwab-client
Version: 2.0.2
Summary: Python library for Charles Schwab API
Home-page: https://github.com/jaycollett/schwabpy
Author: SchwabPy Contributors
License: MIT License
Project-URL: Homepage, https://github.com/jaycollett/schwabpy
Project-URL: Repository, https://github.com/jaycollett/schwabpy
Project-URL: Issues, https://github.com/jaycollett/schwabpy/issues
Keywords: schwab,trading,stocks,options,api,finance
Classifier: Development Status :: 3 - Alpha
Classifier: Intended Audience :: Developers
Classifier: Intended Audience :: Financial and Insurance Industry
Classifier: License :: OSI Approved :: MIT License
Classifier: Operating System :: OS Independent
Classifier: Programming Language :: Python :: 3
Classifier: Programming Language :: Python :: 3.8
Classifier: Programming Language :: Python :: 3.9
Classifier: Programming Language :: Python :: 3.10
Classifier: Programming Language :: Python :: 3.11
Classifier: Programming Language :: Python :: 3.12
Classifier: Topic :: Office/Business :: Financial :: Investment
Requires-Python: >=3.8
License-File: LICENSE
Requires-Dist: requests>=2.31.0
Requires-Dist: cryptography>=41.0.0
Dynamic: home-page
Dynamic: license-file
Dynamic: requires-python
